rb_tocase/__init__.py
rb_tocase/rb_tocase.py
rb_tocase-1.3.2.dist-info/LICENSE
rb_tocase-1.3.2.dist-info/WHEEL
rb_tocase-1.3.2.dist-info/METADATA
rb_tocase-1.3.2.dist-info/RECORD
